pwned/__init__.py
pwned/cli.py
pwned-0.1.2.dist-info/DESCRIPTION.rst
pwned-0.1.2.dist-info/METADATA
pwned-0.1.2.dist-info/RECORD
pwned-0.1.2.dist-info/WHEEL
pwned-0.1.2.dist-info/entry_points.txt
pwned-0.1.2.dist-info/metadata.json
pwned-0.1.2.dist-info/top_level.txt
