Metadata-Version: 2.0
Name: pwned
Version: 0.1.2
Summary: Check if you've been pwned via haveibeenpwned.com
Home-page: https://github.com/SShrike/pwned
Author: Severen Redwood
Author-email: severen@shrike.me
License: GPL-3.0
Keywords: password haveibeenpwned security
Platform: UNKNOWN
Classifier: Development Status :: 1 - Planning
Classifier: Environment :: Console
Classifier: Intended Audience :: End Users/Desktop
Classifier: License :: OSI Approved :: GNU General Public License v3 (GPLv3)
Classifier: Natural Language :: English
Classifier: Operating System :: POSIX :: Linux
Classifier: Operating System :: POSIX :: BSD
Classifier: Programming Language :: Python :: 3
Classifier: Topic :: Security
Classifier: Topic :: Utilities
Requires-Dist: click
Requires-Dist: requests
Provides-Extra: dev
Requires-Dist: twine; extra == 'dev'
Provides-Extra: test
Requires-Dist: pytest; extra == 'test'
